TextTransformer/__init__.py
TextTransformer/transformer.py
texttransformer-0.1.0.dist-info/METADATA
texttransformer-0.1.0.dist-info/WHEEL
texttransformer-0.1.0.dist-info/top_level.txt
texttransformer-0.1.0.dist-info/RECORD
