Metadata-Version: 2.1
Name: texttransformer
Version: 0.1.0
Summary: A simple text transformation library
Home-page: 
Author: Policken
Author-email: a.komlev.0612@gmail.com
Classifier: Programming Language :: Python :: 3
Classifier: License :: OSI Approved :: MIT License
Classifier: Operating System :: OS Independent
Requires-Python: >=3.6
